dna_parser-0.4.0.dist-info/METADATA
dna_parser-0.4.0.dist-info/WHEEL
dna_parser-0.4.0.dist-info/licenses/LICENSE
dna_parser/__init__.py
dna_parser/call_functions.py
dna_parser/dna_parser.cpython-39-x86_64-linux-gnu.so
dna_parser/tfidf_class.py
dna_parser-0.4.0.dist-info/RECORD
