Metadata-Version: 2.4
Name: dna_parser
Version: 0.4.0
Classifier: Programming Language :: Rust
Classifier: Programming Language :: Python :: Implementation :: CPython
Classifier: Programming Language :: Python :: Implementation :: PyPy
Requires-Dist: numpy>=1.16.0
Requires-Dist: scipy>=1.3.0
Requires-Dist: scikit-learn>=1.5.0
Requires-Dist: needletail>=0.7.0
Requires-Dist: pytest ; extra == 'dev'
Requires-Dist: mkdocs ; extra == 'dev'
Provides-Extra: dev
License-File: LICENSE
Requires-Python: >=3.9
